MyyyyyyCalculator/__init__.py
MyyyyyyCalculator-0.1.dist-info/LICENSE.txt
MyyyyyyCalculator-0.1.dist-info/METADATA
MyyyyyyCalculator-0.1.dist-info/WHEEL
MyyyyyyCalculator-0.1.dist-info/top_level.txt
MyyyyyyCalculator-0.1.dist-info/RECORD
