Metadata-Version: 2.1
Name: MyyyyyyCalculator
Version: 0.1
Summary: This Package can help in basic calculator operations
Author: Monin Modi
Author-email: xyz@gmail.com
Classifier: Programming Language :: Python :: 3
Classifier: License :: OSI Approved :: MIT License
Classifier: Operating System :: OS Independent
License-File: LICENSE.txt
